README.md
flask_database.py
setup.py
flask_database.egg-info/PKG-INFO
flask_database.egg-info/SOURCES.txt
flask_database.egg-info/dependency_links.txt
flask_database.egg-info/requires.txt
flask_database.egg-info/top_level.txt